CHANGES.txt
LICENSE.txt
MANIFEST.in
README.txt
bootstrap.py
buildout.cfg
setup.py
src/j01/__init__.py
src/j01.datepicker.egg-info/PKG-INFO
src/j01.datepicker.egg-info/SOURCES.txt
src/j01.datepicker.egg-info/dependency_links.txt
src/j01.datepicker.egg-info/namespace_packages.txt
src/j01.datepicker.egg-info/not-zip-safe
src/j01.datepicker.egg-info/requires.txt
src/j01.datepicker.egg-info/top_level.txt
src/j01/datepicker/README.txt
src/j01/datepicker/__init__.py
src/j01/datepicker/browser.zcml
src/j01/datepicker/configure.zcml
src/j01/datepicker/converter.py
src/j01/datepicker/input.pt
src/j01/datepicker/interfaces.py
src/j01/datepicker/tests.py
src/j01/datepicker/widget.py
src/j01/datepicker/css/j01.datepicker.css
src/j01/datepicker/js/j01.datepicker.js
src/j01/datepicker/less/j01.datepicker.less
src/j01/datepicker/less/source/core.less
src/j01/datepicker/less/source/mixins.less
src/j01/datepicker/less/source/variables.less